<Properties>
  <MonoDevelop.Ide.Workbench ActiveDocument="Assets/Scripts/StageManager.cs">
    <Files>
      <File FileName="Assets/Scripts/LevelManager.cs" Line="14" Column="40" IsPinned="True" />
      <File FileName="Assets/Scripts/StageManager.cs" Line="21" Column="10" IsPinned="True" />
      <File FileName="Assets/Scripts/CamTargetPositioner.cs" />
      <File FileName="Assets/Scripts/OverlayAdder.cs" />
      <File FileName="Assets/Scripts/SpriteColourSwapper.cs" />
      <File FileName="Assets/Scripts/TrailBehaviour.cs" />
      <File FileName="Assets/Scripts/FireInfo.cs" />
      <File FileName="Assets/Scripts/GameManager.cs" />
      <File FileName="Assets/Scripts/TurretController.cs" />
    </Files>
  </MonoDevelop.Ide.Workbench>
  <MonoDevelop.Ide.DebuggingService.PinnedWatches />
  <MonoDevelop.Ide.Workspace ActiveConfiguration="Debug" />
  <MonoDevelop.Ide.ItemProperties.Assembly-CSharp PreferredExecutionTarget="ed7a0967-5600-4760-aeef-346bcdf9acb6" />
  <MonoDevelop.Ide.DebuggingService.Breakpoints>
    <BreakpointStore />
  </MonoDevelop.Ide.DebuggingService.Breakpoints>
  <MultiItemStartupConfigurations />
</Properties>